CHANGES.rst
CONTRIBUTORS.rst
MANIFEST.in
README.rst
setup.cfg
setup.py
docs/LICENSE.GPL
docs/LICENSE.rst
docs/index.rst
src/pas/__init__.py
src/pas.plugins.skipauthentication.egg-info/PKG-INFO
src/pas.plugins.skipauthentication.egg-info/SOURCES.txt
src/pas.plugins.skipauthentication.egg-info/dependency_links.txt
src/pas.plugins.skipauthentication.egg-info/entry_points.txt
src/pas.plugins.skipauthentication.egg-info/namespace_packages.txt
src/pas.plugins.skipauthentication.egg-info/not-zip-safe
src/pas.plugins.skipauthentication.egg-info/requires.txt
src/pas.plugins.skipauthentication.egg-info/top_level.txt
src/pas/plugins/__init__.py
src/pas/plugins/skipauthentication/__init__.py
src/pas/plugins/skipauthentication/configure.zcml
src/pas/plugins/skipauthentication/interfaces.py
src/pas/plugins/skipauthentication/plugin.py
src/pas/plugins/skipauthentication/setuphandlers.py
src/pas/plugins/skipauthentication/browser/__init__.py
src/pas/plugins/skipauthentication/browser/configure.zcml
src/pas/plugins/skipauthentication/browser/controlpanel.py
src/pas/plugins/skipauthentication/browser/templates/add_plugin.pt
src/pas/plugins/skipauthentication/locales/pas.plugins.skipauthentication.pot
src/pas/plugins/skipauthentication/locales/update.sh
src/pas/plugins/skipauthentication/locales/fr/LC_MESSAGES/pas.plugins.skipauthentication.po
src/pas/plugins/skipauthentication/profiles/default/browserlayer.xml
src/pas/plugins/skipauthentication/profiles/default/controlpanel.xml
src/pas/plugins/skipauthentication/profiles/default/metadata.xml
src/pas/plugins/skipauthentication/profiles/default/registry.xml
src/pas/plugins/skipauthentication/profiles/uninstall/browserlayer.xml