Metadata-Version: 1.1
Name: pas.plugins.skipauthentication
Version: 1.0a1
Summary: PAS Plugin to allow authentication for any user for development purpose
Home-page: https://pypi.python.org/pypi/pas.plugins.skipauthentication
Author: Martin Peeters
Author-email: martin.peeters@affinitic.be
License: GPL version 2
Keywords: Python Plone
Platform: UNKNOWN
Classifier: Environment :: Web Environment
Classifier: Framework :: Plone
Classifier: Framework :: Plone :: 5.0
Classifier: Programming Language :: Python
Classifier: Programming Language :: Python :: 2.7
Classifier: Operating System :: OS Independent
Classifier: License :: OSI Approved :: GNU General Public License v2 (GPLv2)
